sse/__init__.py
sse/app.py
sse/utils.py
sse/api/__init__.py
sse/api/urls.py
sse/api/view.py
sse/core/__init__.py
sse/core/channel.py
sse/core/config.py
sse/core/event.py
sse/core/header.py
sse/core/message.py
sse/core/request.py
sse/core/storage/__init__.py
sse/core/storage/base.py
sse/core/storage/memory.py
sse/core/storage/redis_.py
sanic_sse_py3-1.0.8.dist-info/LICENSE
sanic_sse_py3-1.0.8.dist-info/METADATA
sanic_sse_py3-1.0.8.dist-info/WHEEL
sanic_sse_py3-1.0.8.dist-info/top_level.txt
sanic_sse_py3-1.0.8.dist-info/RECORD
